LICENSE
MANIFEST.in
README
README.rst
setup.py
src/admin_customizer/__init__.py
src/admin_customizer/actions.py
src/admin_customizer/admin.py
src/admin_customizer/conf.py
src/admin_customizer/fields.py
src/admin_customizer/managers.py
src/admin_customizer/middleware.py
src/admin_customizer/models.py
src/admin_customizer/orderedset.py
src/admin_customizer/urls.py
src/admin_customizer/views.py
src/admin_customizer/widgets.py
src/admin_customizer/management/__init__.py
src/admin_customizer/management/commands/__init__.py
src/admin_customizer/management/commands/refresh_available_fields.py
src/admin_customizer/migrations/0001_initial.py
src/admin_customizer/migrations/__init__.py
src/admin_customizer/static/admin_customizer/widgets/field-select.css
src/admin_customizer/static/admin_customizer/widgets/field-select.js
src/admin_customizer/static/admin_customizer/widgets/jquery-1.7.1.min.js
src/admin_customizer/templates/admin_customizer/admin_index.html
src/django_admin_customizer.egg-info/PKG-INFO
src/django_admin_customizer.egg-info/SOURCES.txt
src/django_admin_customizer.egg-info/dependency_links.txt
src/django_admin_customizer.egg-info/not-zip-safe
src/django_admin_customizer.egg-info/requires.txt
src/django_admin_customizer.egg-info/top_level.txt